smartx_rfid/__init__.py
smartx_rfid/clients/__init__.py
smartx_rfid/clients/rchlo.py
smartx_rfid/db/__init__.py
smartx_rfid/db/_main.py
smartx_rfid/devices/RFID/R700_IOT/_main.py
smartx_rfid/devices/RFID/R700_IOT/on_event.py
smartx_rfid/devices/RFID/R700_IOT/reader_config_example.py
smartx_rfid/devices/RFID/R700_IOT/reader_helpers.py
smartx_rfid/devices/RFID/R700_IOT/write_commands.py
smartx_rfid/devices/RFID/X714/_main.py
smartx_rfid/devices/RFID/X714/ble_protocol.py
smartx_rfid/devices/RFID/X714/on_receive.py
smartx_rfid/devices/RFID/X714/rfid.py
smartx_rfid/devices/RFID/X714/serial_protocol.py
smartx_rfid/devices/RFID/X714/tcp_protocol.py
smartx_rfid/devices/RFID/X714/write_commands.py
smartx_rfid/devices/__init__.py
smartx_rfid/devices/_base.py
smartx_rfid/devices/device_manager.py
smartx_rfid/devices/generic/SERIAL/_main.py
smartx_rfid/devices/generic/TCP/_main.py
smartx_rfid/devices/generic/TCP/helpers.py
smartx_rfid/parser/__init__.py
smartx_rfid/parser/main.py
smartx_rfid/parser/rfid_tag_parser/__init__.py
smartx_rfid/parser/rfid_tag_parser/exceptions.py
smartx_rfid/parser/rfid_tag_parser/tag_tid_parser.py
smartx_rfid/schemas/__init__.py
smartx_rfid/schemas/events.py
smartx_rfid/schemas/tag.py
smartx_rfid/utils/__init__.py
smartx_rfid/utils/event.py
smartx_rfid/utils/logger_manager.py
smartx_rfid/utils/path.py
smartx_rfid/utils/regex.py
smartx_rfid/utils/tag_list.py
smartx_rfid/webhook/__init__.py
smartx_rfid/webhook/_main.py
smartx_rfid/webhook/xtrack.py
smartx_rfid-2.3.1.dist-info/METADATA
smartx_rfid-2.3.1.dist-info/WHEEL
smartx_rfid-2.3.1.dist-info/licenses/LICENSE
smartx_rfid-2.3.1.dist-info/RECORD
