Metadata-Version: 2.4
Name: smartx-rfid
Version: 2.3.1
Summary: SmartX RFID library
License: MIT
License-File: LICENSE
Keywords: python,library,RFID,smartx,packaging
Author: Gabriel Henrique Pascon
Author-email: gh.pascon@gmail.com
Requires-Python: >=3.11,<4.0
Classifier: Intended Audience :: Developers
Classifier: License :: OSI Approved :: MIT License
Classifier: Operating System :: OS Independent
Classifier: Programming Language :: Python :: 3
Classifier: Programming Language :: Python :: 3.11
Classifier: Programming Language :: Python :: 3.12
Classifier: Programming Language :: Python :: 3.13
Classifier: Programming Language :: Python :: 3.14
Classifier: Topic :: Software Development :: Libraries :: Python Modules
Requires-Dist: bleak (>=1.1.1,<2.0.0)
Requires-Dist: httpx (==0.28.1)
Requires-Dist: psycopg2 (>=2.9.11,<3.0.0)
Requires-Dist: pydantic (>=2.12.5,<3.0.0)
Requires-Dist: pyepc (==0.5.0)
Requires-Dist: pymysql (==1.1.1)
Requires-Dist: pyserial (==3.5)
Requires-Dist: pyserial-asyncio (==0.6)
Requires-Dist: sqlalchemy (==2.0.29)
Project-URL: Documentation, https://github.com/ghpascon/smartx_rfid#readme
Project-URL: Homepage, https://github.com/ghpascon/smartx_rfid
Project-URL: Repository, https://github.com/ghpascon/smartx_rfid
